crunpyroll/__init__.py
crunpyroll/client.py
crunpyroll/errors.py
crunpyroll/session.py
crunpyroll/utils.py
crunpyroll/enums/__init__.py
crunpyroll/enums/api_host.py
crunpyroll/enums/content_type.py
crunpyroll/enums/image_type.py
crunpyroll/methods/__init__.py
crunpyroll/methods/delete_active_stream.py
crunpyroll/methods/get_episodes.py
crunpyroll/methods/get_index.py
crunpyroll/methods/get_license.py
crunpyroll/methods/get_manifest.py
crunpyroll/methods/get_objects.py
crunpyroll/methods/get_profile.py
crunpyroll/methods/get_seasons.py
crunpyroll/methods/get_series.py
crunpyroll/methods/get_streams.py
crunpyroll/methods/search.py
crunpyroll/types/__init__.py
crunpyroll/types/cms.py
crunpyroll/types/content.py
crunpyroll/types/drm.py
crunpyroll/types/episodes.py
crunpyroll/types/hardsub.py
crunpyroll/types/images.py
crunpyroll/types/index.py
crunpyroll/types/manifest.py
crunpyroll/types/movies.py
crunpyroll/types/obj.py
crunpyroll/types/objects.py
crunpyroll/types/profile.py
crunpyroll/types/search.py
crunpyroll/types/seasons.py
crunpyroll/types/series.py
crunpyroll/types/streams.py
crunpyroll/types/subtitles.py
crunpyroll-2.4.5.dist-info/LICENSE
crunpyroll-2.4.5.dist-info/METADATA
crunpyroll-2.4.5.dist-info/WHEEL
crunpyroll-2.4.5.dist-info/top_level.txt
crunpyroll-2.4.5.dist-info/RECORD
