Metadata-Version: 2.1
Name: crunpyroll
Version: 2.4.5
Summary: Async API wrapper for Crunchyroll
Home-page: https://github.com/stefanodvx/crunpyroll
Author: stefanodvx
Author-email: pp.stefanodvx@gmail.com
Project-URL: Tracker, https://github.com/stefanodvx/crunpyroll/issues
Requires-Python: >=3.7
License-File: LICENSE
Requires-Dist: httpx
Requires-Dist: xmltodict
